pymodelling/__init__.py
pymodelling/ode/__init__.py
pymodelling/ode/solver.py
pymodelling/pde/__init__.py
pymodelling/pde/equation.py
pymodelling/pde/solver.py
pymodelling/stochastic/__init__.py
pymodelling/stochastic/gillespie/__init__.py
pymodelling/stochastic/gillespie/model.py
pymodelling/utilities/__init__.py
pymodelling/utilities/progressbar.py
pymodelling-0.1.3.dist-info/LICENSE
pymodelling-0.1.3.dist-info/METADATA
pymodelling-0.1.3.dist-info/WHEEL
pymodelling-0.1.3.dist-info/top_level.txt
pymodelling-0.1.3.dist-info/RECORD
